run_gpt/__init__.py
run_gpt/__main__.py
run_gpt/factory.py
run_gpt/helper.py
run_gpt/logs.py
run_gpt/profile.py
run_gpt/cli/__init__.py
run_gpt/cli/application.py
run_gpt/cli/command_loader.py
run_gpt/cli/commands/__init__.py
run_gpt/cli/commands/about.py
run_gpt/cli/commands/deploy.py
run_gpt/cli/commands/playground.py
run_gpt/cli/commands/quantize.py
run_gpt/cli/commands/serve.py
run_gpt/models/__init__.py
run_gpt/models/chat.py
run_gpt/models/embedding.py
run_gpt/models/generation.py
run_gpt/models/loading.py
run_gpt/models/modeling.py
run_gpt/models/session.py
run_gpt/models/flamingo/__init__.py
run_gpt/models/flamingo/configuration_flamingo.py
run_gpt/models/flamingo/flamingo_lm.py
run_gpt/models/flamingo/flamingo_model.py
run_gpt/models/flamingo/loading.py
run_gpt/models/flamingo/modeling.py
run_gpt/models/llama/__init__.py
run_gpt/models/llama/loading.py
run_gpt/models/llama/modeling.py
run_gpt/models/moss/__init__.py
run_gpt/models/moss/modeling.py
run_gpt/models/pythia/__init__.py
run_gpt/models/pythia/modeling.py
run_gpt/models/rwkv/__init__.py
run_gpt/models/rwkv/modeling.py
run_gpt/models/stablelm/__init__.py
run_gpt/models/stablelm/modeling.py
run_gpt/models/vicuna/__init__.py
run_gpt/models/vicuna/loading.py
run_gpt/models/vicuna/modeling.py
run_gpt/resources/flow.yml.jinja2
run_gpt/serve/__init__.py
run_gpt/serve/flow.py
run_gpt/serve/gateway.py
run_gpt/serve/pydantic_models.py
run_gpt/serve/executors/__init__.py
run_gpt/serve/executors/base.py
run_gpt/serve/executors/flamingo.py
run_gpt/serve/executors/utils.py
run_gpt/serve/playground/__init__.py
run_gpt/serve/playground/gradio.py
run_gpt/serve/playground/gradio_chatbot.py
run_gpt/serve/playground/gradio_css.py
rungpt-0.1.1.dist-info/LICENSE
rungpt-0.1.1.dist-info/METADATA
rungpt-0.1.1.dist-info/WHEEL
rungpt-0.1.1.dist-info/entry_points.txt
rungpt-0.1.1.dist-info/top_level.txt
rungpt-0.1.1.dist-info/RECORD
